README.txt
setup.py
src/oscodepoint/__init__.py
src/oscodepoint.egg-info/PKG-INFO
src/oscodepoint.egg-info/SOURCES.txt
src/oscodepoint.egg-info/dependency_links.txt
src/oscodepoint.egg-info/requires.txt
src/oscodepoint.egg-info/top_level.txt