Metadata-Version: 1.0
Name: oscodepoint
Version: 0.2
Summary: A Python interface to Ordnance Survey's CodePoint-Open data
Home-page: https://github.com/nathforge/oscodepoint
Author: Nathan Reynolds
Author-email: email@nreynolds.co.uk
License: UNKNOWN
Platform: UNKNOWN
